{"nm":"coin_all","layers":[{"nm":"coin_double_euro","ddd":0,"ty":0,"ind":1,"sr":1.0,"ks":{"a":{"k":[200.0,200.0,0.0],"ix":1,"a":0},"p":{"k":[200.0,200.0,0.0],"ix":2,"a":0},"s":{"k":[100.0,100.0,100.0],"ix":6,"a":0},"r":{"k":0.0,"ix":10,"a":0},"o":{"k":100.0,"ix":11,"a":0}},"ao":0,"ip":0.0,"op":44.0,"st":0.0,"bm":0,"refId":"comp_28","w":400.0,"h":400.0},{"nm":"coin_double_dollar","ddd":0,"ty":0,"ind":2,"sr":1.0,"ks":{"a":{"k":[200.0,200.0,0.0],"ix":1,"a":0},"p":{"k":[200.0,200.0,0.0],"ix":2,"a":0},"s":{"k":[100.0,100.0,100.0],"ix":6,"a":0},"r":{"k":0.0,"ix":10,"a":0},"o":{"k":100.0,"ix":11,"a":0}},"ao":0,"ip":44.0,"op":88.0,"st":44.0,"bm":0,"refId":"comp_33","w":400.0,"h":400.0},{"nm":"coin_double_yen","ddd":0,"ty":0,"ind":3,"sr":1.0,"ks":{"a":{"k":[200.0,200.0,0.0],"ix":1,"a":0},"p":{"k":[200.0,200.0,0.0],"ix":2,"a":0},"s":{"k":[100.0,100.0,100.0],"ix":6,"a":0},"r":{"k":0.0,"ix":10,"a":0},"o":{"k":100.0,"ix":11,"a":0}},"ao":0,"ip":88.0,"op":132.0,"st":88.0,"bm":0,"refId":"comp_36","w":400.0,"h":400.0}],"v":"5.1.1","fr":30.0,"ip":0.0,"op":132.0,"w":400,"h":400,"ddd":0,"assets":[{"id":"comp_28","layers":[{"nm":"coin_single_quibble","ddd":0,"ty":0,"ind":1,"sr":1.0,"ks":{"a":{"k":[200.0,200.0,0.0],"ix":1,"a":0},"p":{"k":[200.0,200.0,0.0],"ix":2,"a":0},"s":{"k":[100.0,100.0,100.0],"ix":6,"a":0},"r":{"k":0.0,"ix":10,"a":0},"o":{"k":100.0,"ix":11,"a":0}},"ao":0,"ip":0.0,"op":22.0,"st":0.0,"bm":0,"refId":"comp_29","w":400.0,"h":400.0},{"nm":"coin_single_euro","ddd":0,"ty":0,"ind":2,"sr":1.0,"ks":{"a":{"k":[200.0,200.0,0.0],"ix":1,"a":0},"p":{"k":[200.0,200.0,0.0],"ix":2,"a":0},"s":{"k":[100.0,100.0,100.0],"ix":6,"a":0},"r":{"k":0.0,"ix":10,"a":0},"o":{"k":100.0,"ix":11,"a":0}},"ao":0,"ip":22.0,"op":44.0,"st":22.0,"bm":0,"refId":"comp_31","w":400.0,"h":400.0}]},{"id":"comp_29","layers":[{"nm":"sparkle 2","ddd":0,"ty":4,"ind":1,"sr":1.0,"ks":{"a":{"k":[35.5,28.5,0.0],"ix":1,"a":0},"p":{"k":[169.378,165.244,0.0],"ix":2,"a":0},"s":{"k":[{"t":13.833,"i":{"x":[0.667,0.667,0.667],"y":[1.0,1.0,1.0]},"o":{"x":[0.778,0.778,0.333],"y":[0.0,0.0,0.0]},"s":[0.0,0.0,100.0],"e":[80.0,80.0,100.0],"n":["0p667_1_0p778_0","0p667_1_0p778_0","0p667_1_0p333_0"]},{"t":22.166015625}],"ix":6,"a":1},"r":{"k":0.0,"ix":10,"a":0},"o":{"k":[{"t":15.916,"i":{"x":[0.833],"y":[0.833]},"o":{"x":[0.167],"y":[0.167]},"s":[100.0],"e":[0.0],"n":["0p833_0p833_0p167_0p167"]},{"t":22.166015625}],"ix":11,"a":1}},"ao":0,"ip":0.0,"op":22.0,"st":0.0,"bm":0,"shapes":[{"nm":"null","mn":"ADBE Vector Group","ty":"gr","hd":false,"ix":1,"cix":2,"np":3,"it":[{"nm":"Path 1","mn":"ADBE Vector Shape - Group","ty":"sh","hd":false,"ind":0,"ix":1,"ks":{"k":{"i":[[1.519,-5.107],[10.475,10.309],[4.348,0.814],[-9.99,10.138],[-1.141,4.733],[-9.663,-9.806],[-4.721,-1.139],[9.479,-9.353]],"o":[[-0.807,-4.309],[-10.134,-9.974],[4.721,-1.139],[9.663,-9.806],[1.141,4.733],[9.99,10.138],[-5.092,1.515],[-9.8,9.67]],"v":[[35.5,68.5],[21.415,42.021],[-4.5,28.5],[21.415,13.852],[35.5,-11.5],[49.585,13.852],[75.5,28.5],[50.711,43.148]],"c":true},"ix":2,"a":0}},{"nm":"Stroke 1","mn":"ADBE Vector Graphic - Stroke","ty":"st","hd":false,"o":{"k":100.0,"ix":4,"a":0},"c":{"k":[0.9960784316062927,0.9529411792755127,0.8666666746139526,1.0],"ix":3,"a":0},"w":{"k":[{"t":13.833,"i":{"x":[0.833],"y":[0.833]},"o":{"x":[0.167],"y":[0.167]},"s":[5.0],"e":[9.0],"n":["0p833_0p833_0p167_0p167"]},{"t":18.0,"i":{"x":[0.833],"y":[0.833]},"o":{"x":[0.167],"y":[0.167]},"s":[9.0],"e":[0.0],"n":["0p833_0p833_0p167_0p167"]},{"t":22.166015625}],"ix":5,"a":1},"lc":2,"lj":2},{"nm":"Fill 1","mn":"ADBE Vector Graphic - Fill","ty":"fl","hd":false,"o":{"k":100.0,"ix":5,"a":0},"c":{"k":[0.9960784316062927,0.9529411792755127,0.8666666746139526,1.0],"ix":4,"a":0},"r":1},{"nm":"Transform","ty":"tr","a":{"k":[0.0,0.0],"ix":1,"a":0},"p":{"k":[0.0,0.0],"ix":2,"a":0},"s":{"k":[100.0,100.0],"ix":3,"a":0},"r":{"k":0.0,"ix":6,"a":0},"sk":{"k":0.0,"ix":4,"a":0},"sa":{"k":0.0,"ix":5,"a":0},"o":{"k":100.0,"ix":7,"a":0}}]}]},{"nm":"sparkle","ddd":0,"ty":4,"ind":2,"sr":1.0,"ks":{"a":{"k":[35.5,28.5,0.0],"ix":1,"a":0},"p":{"k":[235.5,228.5,0.0],"ix":2,"a":0},"s":{"k":[{"t":7.583,"i":{"x":[0.667,0.667,0.667],"y":[1.0,1.0,1.0]},"o":{"x":[0.778,0.778,0.333],"y":[0.0,0.0,0.0]},"s":[0.0,0.0,100.0],"e":[100.0,100.0,100.0],"n":["0p667_1_0p778_0","0p667_1_0p778_0","0p667_1_0p333_0"]},{"t":15.916015625}],"ix":6,"a":1},"r":{"k":0.0,"ix":10,"a":0},"o":{"k":[{"t":11.75,"i":{"x":[0.833],"y":[0.833]},"o":{"x":[0.167],"y":[0.167]},"s":[100.0],"e":[0.0],"n":["0p833_0p833_0p167_0p167"]},{"t":18.0}],"ix":11,"a":1}},"ao":0,"ip":0.0,"op":22.0,"st":0.0,"bm":0,"shapes":[{"nm":"null","mn":"ADBE Vector Group","ty":"gr","hd":false,"ix":1,"cix":2,"np":3,"it":[{"nm":"Path 1","mn":"ADBE Vector Shape - Group","ty":"sh","hd":false,"ind":0,"ix":1,"ks":{"k":{"i":[[1.519,-5.107],[10.475,10.309],[4.348,0.814],[-9.99,10.138],[-1.141,4.733],[-9.663,-9.806],[-4.721,-1.139],[9.479,-9.353]],"o":[[-0.807,-4.309],[-10.134,-9.974],[4.721,-1.139],[9.663,-9.806],[1.141,4.733],[9.99,10.138],[-5.092,1.515],[-9.8,9.67]],"v":[[35.5,68.5],[21.415,42.021],[-4.5,28.5],[21.415,13.852],[35.5,-11.5],[49.585,13.852],[75.5,28.5],[50.711,43.148]],"c":true},"ix":2,"a":0}},{"nm":"Fill 1","mn":"ADBE Vector Graphic - Fill","ty":"fl","hd":false,"o":{"k":100.0,"ix":5,"a":0},"c":{"k":[0.9960784316062927,0.9529411792755127,0.8666666746139526,1.0],"ix":4,"a":0},"r":1},{"nm":"Stroke 1","mn":"ADBE Vector Graphic - Stroke","ty":"st","hd":false,"o":{"k":100.0,"ix":4,"a":0},"c":{"k":[0.9960784316062927,0.9529411792755127,0.8666666746139526,1.0],"ix":3,"a":0},"w":{"k":[{"t":7.583,"i":{"x":[0.833],"y":[0.833]},"o":{"x":[0.167],"y":[0.167]},"s":[5.0],"e":[9.0],"n":["0p833_0p833_0p167_0p167"]},{"t":11.75,"i":{"x":[0.833],"y":[0.833]},"o":{"x":[0.167],"y":[0.167]},"s":[9.0],"e":[0.0],"n":["0p833_0p833_0p167_0p167"]},{"t":15.916015625}],"ix":5,"a":1},"lc":2,"lj":2},{"nm":"Transform","ty":"tr","a":{"k":[0.0,0.0],"ix":1,"a":0},"p":{"k":[0.0,0.0],"ix":2,"a":0},"s":{"k":[100.0,100.0],"ix":3,"a":0},"r":{"k":0.0,"ix":6,"a":0},"sk":{"k":0.0,"ix":4,"a":0},"sa":{"k":0.0,"ix":5,"a":0},"o":{"k":100.0,"ix":7,"a":0}}]}]},{"nm":"coin_face_quibble","ddd":0,"ty":0,"ind":3,"sr":1.0,"ks":{"a":{"k":[200.0,200.0,0.0],"ix":1,"a":0},"p":{"k":[{"t":0.0,"i":{"x":0.0,"y":1.0},"o":{"x":0.333,"y":0.0},"s":[210.445,200.914,0.0],"e":[200.445,200.914,0.0],"ti":[0.0,0.0,0.0],"to":[0.0,0.0,0.0],"n":"0_1_0p333_0"},{"t":12.0,"i":{"x":0.667,"y":1.0},"o":{"x":1.0,"y":0.0},"s":[200.445,200.914,0.0],"e":[190.0,200.914,0.0],"ti":[0.0,0.0,0.0],"to":[0.0,0.0,0.0],"n":"0p667_1_1_0"},{"t":23.0}],"ix":2,"a":1},"s":{"k":[{"t":0.0,"i":{"x":[0.0,0.667,0.667],"y":[1.0,1.0,1.0]},"o":{"x":[0.333,0.333,0.333],"y":[0.0,0.0,0.0]},"s":[0.0,100.0,100.0],"e":[100.0,100.0,100.0],"n":["0_1_0p333_0","0p667_1_0p333_0","0p667_1_0p333_0"]},{"t":12.0,"i":{"x":[0.667,0.667,0.667],"y":[1.0,1.0,1.0]},"o":{"x":[1.0,0.333,0.333],"y":[0.0,0.0,0.0]},"s":[100.0,100.0,100.0],"e":[0.0,100.0,100.0],"n":["0p667_1_1_0","0p667_1_0p333_0","0p667_1_0p333_0"]},{"t":23.0}],"ix":6,"a":1},"r":{"k":0.0,"ix":10,"a":0},"o":{"k":100.0,"ix":11,"a":0}},"ao":0,"ip":0.0,"op":22.0,"st":0.0,"bm":0,"refId":"comp_30","w":400.0,"h":400.0},{"nm":"coin_round_side","ddd":0,"ty":4,"ind":4,"sr":1.0,"ks":{"a":{"k":[0.445,0.914,0.0],"ix":1,"a":0},"p":{"k":[{"t":0.0,"i":{"x":0.0,"y":1.0},"o":{"x":0.333,"y":0.0},"s":[190.445,200.914,0.0],"e":[200.445,200.914,0.0],"ti":[0.0,0.0,0.0],"to":[0.0,0.0,0.0],"n":"0_1_0p333_0"},{"t":12.0,"i":{"x":0.667,"y":1.0},"o":{"x":1.0,"y":0.0},"s":[200.445,200.914,0.0],"e":[210.0,200.914,0.0],"ti":[0.0,0.0,0.0],"to":[0.0,0.0,0.0],"n":"0p667_1_1_0"},{"t":23.0}],"ix":2,"a":1},"s":{"k":[{"t":0.0,"i":{"x":[0.0,0.667,0.667],"y":[1.0,1.0,1.0]},"o":{"x":[0.333,0.333,0.333],"y":[0.0,0.0,0.0]},"s":[0.0,100.0,100.0],"e":[100.0,100.0,100.0],"n":["0_1_0p333_0","0p667_1_0p333_0","0p667_1_0p333_0"]},{"t":12.0,"i":{"x":[0.667,0.667,0.667],"y":[1.0,1.0,1.0]},"o":{"x":[1.0,0.333,0.333],"y":[0.0,0.0,0.0]},"s":[100.0,100.0,100.0],"e":[0.0,100.0,100.0],"n":["0p667_1_1_0","0p667_1_0p333_0","0p667_1_0p333_0"]},{"t":23.0}],"ix":6,"a":1},"r":{"k":0.0,"ix":10,"a":0},"o":{"k":100.0,"ix":11,"a":0}},"ao":0,"ip":0.0,"op":22.0,"st":0.0,"bm":0,"shapes":[{"nm":"null","mn":"ADBE Vector Group","ty":"gr","hd":false,"ix":1,"cix":2,"np":2,"it":[{"nm":"Ellipse Path 1","mn":"ADBE Vector Shape - Ellipse","ty":"el","hd":false,"d":1,"p":{"k":[0.0,0.0],"ix":3,"a":0},"s":{"k":[157.975,157.975],"ix":2,"a":0}},{"nm":"Fill 1","mn":"ADBE Vector Graphic - Fill","ty":"fl","hd":false,"o":{"k":100.0,"ix":5,"a":0},"c":{"k":[0.9960784316062927,0.8967320322990417,0.6980392336845398,1.0],"ix":4,"a":0},"r":1},{"nm":"Transform","ty":"tr","a":{"k":[0.0,0.0],"ix":1,"a":0},"p":{"k":[0.445,0.914],"ix":2,"a":0},"s":{"k":[100.0,100.0],"ix":3,"a":0},"r":{"k":0.0,"ix":6,"a":0},"sk":{"k":0.0,"ix":4,"a":0},"sa":{"k":0.0,"ix":5,"a":0},"o":{"k":100.0,"ix":7,"a":0}}]}]},{"nm":"coin_side","ddd":0,"ty":4,"ind":5,"sr":1.0,"ks":{"a":{"k":[0.5,1.0,0.0],"ix":1,"a":0},"p":{"k":[200.5,201.0,0.0],"ix":2,"a":0},"s":{"k":[100.0,99.7,100.0],"ix":6,"a":0},"r":{"k":0.0,"ix":10,"a":0},"o":{"k":100.0,"ix":11,"a":0}},"ao":0,"ip":0.0,"op":22.0,"st":0.0,"bm":0,"shapes":[{"nm":"null","mn":"ADBE Vector Group","ty":"gr","hd":false,"ix":1,"cix":2,"np":2,"it":[{"nm":"Rectangle Path 1","mn":"ADBE Vector Shape - Rect","ty":"rc","hd":false,"d":1,"p":{"k":[0.0,0.0],"ix":3,"a":0},"s":{"k":[20.5,157.0],"ix":2,"a":0},"r":{"k":0.0,"ix":4,"a":0}},{"nm":"Fill 1","mn":"ADBE Vector Graphic - Fill","ty":"fl","hd":false,"o":{"k":100.0,"ix":5,"a":0},"c":{"k":[0.9960784316062927,0.8967320322990417,0.6980392336845398,1.0],"ix":4,"a":0},"r":1},{"nm":"Transform","ty":"tr","a":{"k":[0.0,0.0],"ix":1,"a":0},"p":{"k":[0.5,1.0],"ix":2,"a":0},"s":{"k":[100.0,100.0],"ix":3,"a":0},"r":{"k":0.0,"ix":6,"a":0},"sk":{"k":0.0,"ix":4,"a":0},"sa":{"k":0.0,"ix":5,"a":0},"o":{"k":100.0,"ix":7,"a":0}}]}]}]},{"id":"comp_30","layers":[{"nm":"coin_quibble","ddd":0,"ty":4,"ind":1,"sr":1.0,"ks":{"a":{"k":[0.0,1.0,0.0],"ix":1,"a":0},"p":{"k":[200.0,201.0,0.0],"ix":2,"a":0},"s":{"k":[100.0,100.0,100.0],"ix":6,"a":0},"r":{"k":0.0,"ix":10,"a":0},"o":{"k":100.0,"ix":11,"a":0}},"ao":0,"ip":0.0,"op":200.0,"st":0.0,"bm":0,"shapes":[{"nm":"null","mn":"ADBE Vector Group","ty":"gr","hd":false,"ix":1,"cix":2,"np":3,"it":[{"nm":"Path 1","mn":"ADBE Vector Shape - Group","ty":"sh","hd":false,"ind":0,"ix":1,"ks":{"k":{"i":[[2.583,0.0],[0.0,13.614],[-13.614,0.0],[-3.474,-9.434],[1.878,0.0],[0.0,-9.981],[-4.647,-3.271]],"o":[[-13.614,0.0],[0.0,-13.614],[10.625,0.0],[-1.693,-0.529],[-9.981,0.0],[0.0,6.119],[-2.345,0.741]],"v":[[0.0,25.688],[-24.688,1.0],[0.0,-23.688],[23.18,-7.509],[17.802,-8.32],[-0.273,9.755],[7.415,24.551]],"c":true},"ix":2,"a":0}},{"nm":"Path 2","mn":"ADBE Vector Shape - Group","ty":"sh","hd":false,"ind":1,"ix":2,"ks":{"k":{"i":[[22.607,0.0],[0.0,-22.607],[-22.607,0.0],[0.0,22.607]],"o":[[-22.607,0.0],[0.0,22.607],[22.607,0.0],[0.0,-22.607]],"v":[[0.0,-40.0],[-41.0,1.0],[0.0,42.0],[41.0,1.0]],"c":true},"ix":2,"a":0}},{"nm":"Fill 1","mn":"ADBE Vector Graphic - Fill","ty":"fl","hd":false,"o":{"k":100.0,"ix":5,"a":0},"c":{"k":[1.0,0.5568627715110779,0.9254902005195618,1.0],"ix":4,"a":0},"r":1},{"nm":"Transform","ty":"tr","a":{"k":[0.0,0.0],"ix":1,"a":0},"p":{"k":[0.0,0.0],"ix":2,"a":0},"s":{"k":[100.0,100.0],"ix":3,"a":0},"r":{"k":0.0,"ix":6,"a":0},"sk":{"k":0.0,"ix":4,"a":0},"sa":{"k":0.0,"ix":5,"a":0},"o":{"k":100.0,"ix":7,"a":0}}]}]},{"nm":"coin_middle","ddd":0,"ty":4,"ind":3,"sr":1.0,"ks":{"a":{"k":[0.445,1.417,0.0],"ix":1,"a":0},"p":{"k":[200.0,200.0,0.0],"ix":2,"a":0},"s":{"k":[100.0,100.0,100.0],"ix":6,"a":0},"r":{"k":0.0,"ix":10,"a":0},"o":{"k":100.0,"ix":11,"a":0}},"ao":0,"ip":0.0,"op":200.0,"st":0.0,"bm":0,"shapes":[{"nm":"null","mn":"ADBE Vector Group","ty":"gr","hd":false,"ix":1,"cix":2,"np":2,"it":[{"nm":"Ellipse Path 1","mn":"ADBE Vector Shape - Ellipse","ty":"el","hd":false,"d":1,"p":{"k":[0.0,0.0],"ix":3,"a":0},"s":{"k":[120.746,120.746],"ix":2,"a":0}},{"nm":"Fill 1","mn":"ADBE Vector Graphic - Fill","ty":"fl","hd":false,"o":{"k":100.0,"ix":5,"a":0},"c":{"k":[0.9882352948188782,0.8235294222831726,0.9882352948188782,1.0],"ix":4,"a":0},"r":1},{"nm":"Transform","ty":"tr","a":{"k":[0.0,0.0],"ix":1,"a":0},"p":{"k":[0.445,1.417],"ix":2,"a":0},"s":{"k":[100.0,100.0],"ix":3,"a":0},"r":{"k":0.0,"ix":6,"a":0},"sk":{"k":0.0,"ix":4,"a":0},"sa":{"k":0.0,"ix":5,"a":0},"o":{"k":100.0,"ix":7,"a":0}}]}]},{"nm":"coin_back","ddd":0,"ty":4,"ind":4,"sr":1.0,"ks":{"a":{"k":[0.445,0.914,0.0],"ix":1,"a":0},"p":{"k":[200.445,200.914,0.0],"ix":2,"a":0},"s":{"k":[100.0,100.0,100.0],"ix":6,"a":0},"r":{"k":0.0,"ix":10,"a":0},"o":{"k":100.0,"ix":11,"a":0}},"ao":0,"ip":0.0,"op":200.0,"st":0.0,"bm":0,"shapes":[{"nm":"null","mn":"ADBE Vector Group","ty":"gr","hd":false,"ix":1,"cix":2,"np":2,"it":[{"nm":"Ellipse Path 1","mn":"ADBE Vector Shape - Ellipse","ty":"el","hd":false,"d":1,"p":{"k":[0.0,0.0],"ix":3,"a":0},"s":{"k":[157.975,157.975],"ix":2,"a":0}},{"nm":"Fill 1","mn":"ADBE Vector Graphic - Fill","ty":"fl","hd":false,"o":{"k":100.0,"ix":5,"a":0},"c":{"k":[1.0,0.5568627715110779,0.9254902005195618,1.0],"ix":4,"a":0},"r":1},{"nm":"Transform","ty":"tr","a":{"k":[0.0,0.0],"ix":1,"a":0},"p":{"k":[0.445,0.914],"ix":2,"a":0},"s":{"k":[100.0,100.0],"ix":3,"a":0},"r":{"k":0.0,"ix":6,"a":0},"sk":{"k":0.0,"ix":4,"a":0},"sa":{"k":0.0,"ix":5,"a":0},"o":{"k":100.0,"ix":7,"a":0}}]}]}]},{"id":"comp_31","layers":[{"nm":"coin_face_euro","ddd":0,"ty":0,"ind":3,"sr":1.0,"ks":{"a":{"k":[200.0,200.0,0.0],"ix":1,"a":0},"p":{"k":[{"t":0.0,"i":{"x":0.0,"y":1.0},"o":{"x":0.333,"y":0.0},"s":[210.445,200.914,0.0],"e":[200.445,200.914,0.0],"ti":[0.0,0.0,0.0],"to":[0.0,0.0,0.0],"n":"0_1_0p333_0"},{"t":12.0,"i":{"x":0.667,"y":1.0},"o":{"x":1.0,"y":0.0},"s":[200.445,200.914,0.0],"e":[190.0,200.914,0.0],"ti":[0.0,0.0,0.0],"to":[0.0,0.0,0.0],"n":"0p667_1_1_0"},{"t":23.0}],"ix":2,"a":1},"s":{"k":[{"t":0.0,"i":{"x":[0.0,0.667,0.667],"y":[1.0,1.0,1.0]},"o":{"x":[0.333,0.333,0.333],"y":[0.0,0.0,0.0]},"s":[0.0,100.0,100.0],"e":[100.0,100.0,100.0],"n":["0_1_0p333_0","0p667_1_0p333_0","0p667_1_0p333_0"]},{"t":12.0,"i":{"x":[0.667,0.667,0.667],"y":[1.0,1.0,1.0]},"o":{"x":[1.0,0.333,0.333],"y":[0.0,0.0,0.0]},"s":[100.0,100.0,100.0],"e":[0.0,100.0,100.0],"n":["0p667_1_1_0","0p667_1_0p333_0","0p667_1_0p333_0"]},{"t":23.0}],"ix":6,"a":1},"r":{"k":0.0,"ix":10,"a":0},"o":{"k":100.0,"ix":11,"a":0}},"ao":0,"ip":0.0,"op":22.0,"st":0.0,"bm":0,"refId":"comp_32","w":400.0,"h":400.0},{"nm":"coin_back_side_round","ddd":0,"ty":4,"ind":4,"sr":1.0,"ks":{"a":{"k":[0.445,0.914,0.0],"ix":1,"a":0},"p":{"k":[{"t":0.0,"i":{"x":0.0,"y":1.0},"o":{"x":0.333,"y":0.0},"s":[190.445,200.914,0.0],"e":[200.445,200.914,0.0],"ti":[0.0,0.0,0.0],"to":[0.0,0.0,0.0],"n":"0_1_0p333_0"},{"t":12.0,"i":{"x":0.667,"y":1.0},"o":{"x":1.0,"y":0.0},"s":[200.445,200.914,0.0],"e":[210.0,200.914,0.0],"ti":[0.0,0.0,0.0],"to":[0.0,0.0,0.0],"n":"0p667_1_1_0"},{"t":23.0}],"ix":2,"a":1},"s":{"k":[{"t":0.0,"i":{"x":[0.0,0.667,0.667],"y":[1.0,1.0,1.0]},"o":{"x":[0.333,0.333,0.333],"y":[0.0,0.0,0.0]},"s":[0.0,100.0,100.0],"e":[100.0,100.0,100.0],"n":["0_1_0p333_0","0p667_1_0p333_0","0p667_1_0p333_0"]},{"t":12.0,"i":{"x":[0.667,0.667,0.667],"y":[1.0,1.0,1.0]},"o":{"x":[1.0,0.333,0.333],"y":[0.0,0.0,0.0]},"s":[100.0,100.0,100.0],"e":[0.0,100.0,100.0],"n":["0p667_1_1_0","0p667_1_0p333_0","0p667_1_0p333_0"]},{"t":23.0}],"ix":6,"a":1},"r":{"k":0.0,"ix":10,"a":0},"o":{"k":100.0,"ix":11,"a":0}},"ao":0,"ip":0.0,"op":22.0,"st":0.0,"bm":0,"shapes":[{"nm":"null","mn":"ADBE Vector Group","ty":"gr","hd":false,"ix":1,"cix":2,"np":2,"it":[{"nm":"Ellipse Path 1","mn":"ADBE Vector Shape - Ellipse","ty":"el","hd":false,"d":1,"p":{"k":[0.0,0.0],"ix":3,"a":0},"s":{"k":[157.975,157.975],"ix":2,"a":0}},{"nm":"Fill 1","mn":"ADBE Vector Graphic - Fill","ty":"fl","hd":false,"o":{"k":100.0,"ix":5,"a":0},"c":{"k":[0.9960784316062927,0.8967320322990417,0.6980392336845398,1.0],"ix":4,"a":0},"r":1},{"nm":"Transform","ty":"tr","a":{"k":[0.0,0.0],"ix":1,"a":0},"p":{"k":[0.445,0.914],"ix":2,"a":0},"s":{"k":[100.0,100.0],"ix":3,"a":0},"r":{"k":0.0,"ix":6,"a":0},"sk":{"k":0.0,"ix":4,"a":0},"sa":{"k":0.0,"ix":5,"a":0},"o":{"k":100.0,"ix":7,"a":0}}]}]},{"nm":"coin_side","ddd":0,"ty":4,"ind":5,"sr":1.0,"ks":{"a":{"k":[0.5,1.0,0.0],"ix":1,"a":0},"p":{"k":[200.5,201.0,0.0],"ix":2,"a":0},"s":{"k":[100.0,99.7,100.0],"ix":6,"a":0},"r":{"k":0.0,"ix":10,"a":0},"o":{"k":100.0,"ix":11,"a":0}},"ao":0,"ip":0.0,"op":22.0,"st":0.0,"bm":0,"shapes":[{"nm":"null","mn":"ADBE Vector Group","ty":"gr","hd":false,"ix":1,"cix":2,"np":2,"it":[{"nm":"Rectangle Path 1","mn":"ADBE Vector Shape - Rect","ty":"rc","hd":false,"d":1,"p":{"k":[0.0,0.0],"ix":3,"a":0},"s":{"k":[20.5,157.0],"ix":2,"a":0},"r":{"k":0.0,"ix":4,"a":0}},{"nm":"Fill 1","mn":"ADBE Vector Graphic - Fill","ty":"fl","hd":false,"o":{"k":100.0,"ix":5,"a":0},"c":{"k":[0.9960784316062927,0.8967320322990417,0.6980392336845398,1.0],"ix":4,"a":0},"r":1},{"nm":"Transform","ty":"tr","a":{"k":[0.0,0.0],"ix":1,"a":0},"p":{"k":[0.5,1.0],"ix":2,"a":0},"s":{"k":[100.0,100.0],"ix":3,"a":0},"r":{"k":0.0,"ix":6,"a":0},"sk":{"k":0.0,"ix":4,"a":0},"sa":{"k":0.0,"ix":5,"a":0},"o":{"k":100.0,"ix":7,"a":0}}]}]}]},{"id":"comp_32","layers":[{"nm":"coin_euro","ddd":0,"ty":4,"ind":1,"sr":1.0,"ks":{"a":{"k":[-9.93,0.849,0.0],"ix":1,"a":0},"p":{"k":[190.07,200.849,0.0],"ix":2,"a":0},"s":{"k":[100.0,100.0,100.0],"ix":6,"a":0},"r":{"k":0.0,"ix":10,"a":0},"o":{"k":100.0,"ix":11,"a":0}},"ao":0,"ip":0.0,"op":200.0,"st":0.0,"bm":0,"shapes":[{"nm":"null","mn":"ADBE Vector Group","ty":"gr","hd":false,"ix":1,"cix":2,"np":1,"it":[{"nm":"null","mn":"ADBE Vector Group","ty":"gr","hd":false,"ix":1,"cix":2,"np":1,"it":[{"nm":"null","mn":"ADBE Vector Group","ty":"gr","hd":false,"ix":1,"cix":2,"np":2,"it":[{"nm":"Path 1","mn":"ADBE Vector Shape - Group","ty":"sh","hd":false,"ind":0,"ix":1,"ks":{"k":{"i":[[1.195,-3.038],[0.0,0.0],[1.522,-0.094],[0.0,0.0],[0.151,2.451],[0.0,0.0],[-2.237,0.138],[0.0,0.0]],"o":[[0.0,0.0],[-0.601,1.527],[0.0,0.0],[-2.237,0.138],[0.0,0.0],[-0.151,-2.451],[0.0,0.0],[3.027,-0.187]],"v":[[13.027,7.861],[13.027,7.861],[9.569,10.501],[-41.026,13.62],[-45.35,9.433],[-45.35,9.433],[-41.573,4.745],[9.022,1.626]],"c":true},"ix":2,"a":0}},{"nm":"Fill 1","mn":"ADBE Vector Graphic - Fill","ty":"fl","hd":false,"o":{"k":100.0,"ix":5,"a":0},"c":{"k":[1.0,0.5568627715110779,0.9254902005195618,1.0],"ix":4,"a":0},"r":1},{"nm":"Transform","ty":"tr","a":{"k":[0.0,0.0],"ix":1,"a":0},"p":{"k":[0.0,0.0],"ix":2,"a":0},"s":{"k":[100.0,100.0],"ix":3,"a":0},"r":{"k":0.0,"ix":6,"a":0},"sk":{"k":0.0,"ix":4,"a":0},"sa":{"k":0.0,"ix":5,"a":0},"o":{"k":100.0,"ix":7,"a":0}}]},{"nm":"Transform","ty":"tr","a":{"k":[0.0,0.0],"ix":1,"a":0},"p":{"k":[0.0,0.0],"ix":2,"a":0},"s":{"k":[100.0,100.0],"ix":3,"a":0},"r":{"k":0.0,"ix":6,"a":0},"sk":{"k":0.0,"ix":4,"a":0},"sa":{"k":0.0,"ix":5,"a":0},"o":{"k":100.0,"ix":7,"a":0}}]},{"nm":"Transform","ty":"tr","a":{"k":[0.0,0.0],"ix":1,"a":0},"p":{"k":[0.0,0.0],"ix":2,"a":0},"s":{"k":[100.0,100.0],"ix":3,"a":0},"r":{"k":0.0,"ix":6,"a":0},"sk":{"k":0.0,"ix":4,"a":0},"sa":{"k":0.0,"ix":5,"a":0},"o":{"k":100.0,"ix":7,"a":0}}]},{"nm":"null","mn":"ADBE Vector Group","ty":"gr","hd":false,"ix":2,"cix":2,"np":1,"it":[{"nm":"null","mn":"ADBE Vector Group","ty":"gr","hd":false,"ix":1,"cix":2,"np":1,"it":[{"nm":"null","mn":"ADBE Vector Group","ty":"gr","hd":false,"ix":1,"cix":2,"np":2,"it":[{"nm":"Path 1","mn":"ADBE Vector Shape - Group","ty":"sh","hd":false,"ind":0,"ix":1,"ks":{"k":{"i":[[1.195,-3.038],[0.0,0.0],[1.522,-0.094],[0.0,0.0],[0.151,2.451],[0.0,0.0],[-2.237,0.138],[0.0,0.0]],"o":[[0.0,0.0],[-0.601,1.527],[0.0,0.0],[-2.237,0.138],[0.0,0.0],[-0.151,-2.451],[0.0,0.0],[3.027,-0.187]],"v":[[18.327,-5.617],[18.327,-5.617],[14.869,-2.976],[-41.833,0.519],[-46.158,-3.669],[-46.158,-3.669],[-42.381,-8.356],[14.322,-11.852]],"c":true},"ix":2,"a":0}},{"nm":"Fill 1","mn":"ADBE Vector Graphic - Fill","ty":"fl","hd":false,"o":{"k":100.0,"ix":5,"a":0},"c":{"k":[1.0,0.5568627715110779,0.9254902005195618,1.0],"ix":4,"a":0},"r":1},{"nm":"Transform","ty":"tr","a":{"k":[0.0,0.0],"ix":1,"a":0},"p":{"k":[0.0,0.0],"ix":2,"a":0},"s":{"k":[100.0,100.0],"ix":3,"a":0},"r":{"k":0.0,"ix":6,"a":0},"sk":{"k":0.0,"ix":4,"a":0},"sa":{"k":0.0,"ix":5,"a":0},"o":{"k":100.0,"ix":7,"a":0}}]},{"nm":"Transform","ty":"tr","a":{"k":[0.0,0.0],"ix":1,"a":0},"p":{"k":[0.0,0.0],"ix":2,"a":0},"s":{"k":[100.0,100.0],"ix":3,"a":0},"r":{"k":0.0,"ix":6,"a":0},"sk":{"k":0.0,"ix":4,"a":0},"sa":{"k":0.0,"ix":5,"a":0},"o":{"k":100.0,"ix":7,"a":0}}]},{"nm":"Transform","ty":"tr","a":{"k":[0.0,0.0],"ix":1,"a":0},"p":{"k":[0.0,0.0],"ix":2,"a":0},"s":{"k":[100.0,100.0],"ix":3,"a":0},"r":{"k":0.0,"ix":6,"a":0},"sk":{"k":0.0,"ix":4,"a":0},"sa":{"k":0.0,"ix":5,"a":0},"o":{"k":100.0,"ix":7,"a":0}}]},{"nm":"null","mn":"ADBE Vector Group","ty":"gr","hd":false,"ix":3,"cix":2,"np":1,"it":[{"nm":"null","mn":"ADBE Vector Group","ty":"gr","hd":false,"ix":1,"cix":2,"np":1,"it":[{"nm":"null","mn":"ADBE Vector Group","ty":"gr","hd":false,"ix":1,"cix":2,"np":2,"it":[{"nm":"Path 1","mn":"ADBE Vector Shape - Group","ty":"sh","hd":false,"ind":0,"ix":1,"ks":{"k":{"i":[[10.105,-0.624],[0.712,0.005],[7.099,7.124],[0.417,10.796],[-7.104,8.001],[-8.798,1.152],[-5.671,-4.331],[1.565,-1.992],[0.0,0.0],[1.716,1.282],[8.554,-1.119],[-0.638,-16.51],[-5.393,-5.411],[-6.357,-0.043],[-3.538,3.342],[-1.527,-1.54],[0.0,0.0],[1.814,-1.734]],"o":[[-0.69,0.043],[-9.029,-0.062],[-7.558,-7.585],[-0.417,-10.8],[6.368,-7.172],[12.112,-1.582],[1.99,1.52],[0.0,0.0],[-1.341,1.706],[-4.072,-3.042],[-12.433,1.627],[0.294,7.6],[5.118,5.136],[7.623,0.051],[1.554,-1.468],[0.0,0.0],[1.791,1.806],[-4.537,4.337]],"v":[[2.572,41.962],[0.471,42.02],[-24.907,30.713],[-37.273,2.21],[-26.904,-26.944],[-3.039,-40.042],[24.539,-31.863],[25.338,-25.3],[23.566,-23.045],[18.205,-22.309],[-1.635,-28.273],[-26.456,1.841],[-17.638,22.018],[0.417,30.168],[17.519,22.718],[22.923,22.843],[24.933,24.87],[24.881,31.495]],"c":true},"ix":2,"a":0}},{"nm":"Fill 1","mn":"ADBE Vector Graphic - Fill","ty":"fl","hd":false,"o":{"k":100.0,"ix":5,"a":0},"c":{"k":[1.0,0.5568627715110779,0.9254902005195618,1.0],"ix":4,"a":0},"r":1},{"nm":"Transform","ty":"tr","a":{"k":[0.0,0.0],"ix":1,"a":0},"p":{"k":[0.0,0.0],"ix":2,"a":0},"s":{"k":[100.0,100.0],"ix":3,"a":0},"r":{"k":0.0,"ix":6,"a":0},"sk":{"k":0.0,"ix":4,"a":0},"sa":{"k":0.0,"ix":5,"a":0},"o":{"k":100.0,"ix":7,"a":0}}]},{"nm":"Transform","ty":"tr","a":{"k":[0.0,0.0],"ix":1,"a":0},"p":{"k":[0.0,0.0],"ix":2,"a":0},"s":{"k":[100.0,100.0],"ix":3,"a":0},"r":{"k":0.0,"ix":6,"a":0},"sk":{"k":0.0,"ix":4,"a":0},"sa":{"k":0.0,"ix":5,"a":0},"o":{"k":100.0,"ix":7,"a":0}}]},{"nm":"Transform","ty":"tr","a":{"k":[0.0,0.0],"ix":1,"a":0},"p":{"k":[0.0,0.0],"ix":2,"a":0},"s":{"k":[100.0,100.0],"ix":3,"a":0},"r":{"k":0.0,"ix":6,"a":0},"sk":{"k":0.0,"ix":4,"a":0},"sa":{"k":0.0,"ix":5,"a":0},"o":{"k":100.0,"ix":7,"a":0}}]}]},{"nm":"coin_middle","ddd":0,"ty":4,"ind":2,"sr":1.0,"ks":{"a":{"k":[0.445,1.417,0.0],"ix":1,"a":0},"p":{"k":[200.0,200.0,0.0],"ix":2,"a":0},"s":{"k":[100.0,100.0,100.0],"ix":6,"a":0},"r":{"k":0.0,"ix":10,"a":0},"o":{"k":100.0,"ix":11,"a":0}},"ao":0,"ip":0.0,"op":200.0,"st":0.0,"bm":0,"shapes":[{"nm":"null","mn":"ADBE Vector Group","ty":"gr","hd":false,"ix":1,"cix":2,"np":2,"it":[{"nm":"Ellipse Path 1","mn":"ADBE Vector Shape - Ellipse","ty":"el","hd":false,"d":1,"p":{"k":[0.0,0.0],"ix":3,"a":0},"s":{"k":[120.746,120.746],"ix":2,"a":0}},{"nm":"Fill 1","mn":"ADBE Vector Graphic - Fill","ty":"fl","hd":false,"o":{"k":100.0,"ix":5,"a":0},"c":{"k":[0.9882352948188782,0.8235294222831726,0.9882352948188782,1.0],"ix":4,"a":0},"r":1},{"nm":"Transform","ty":"tr","a":{"k":[0.0,0.0],"ix":1,"a":0},"p":{"k":[0.445,1.417],"ix":2,"a":0},"s":{"k":[100.0,100.0],"ix":3,"a":0},"r":{"k":0.0,"ix":6,"a":0},"sk":{"k":0.0,"ix":4,"a":0},"sa":{"k":0.0,"ix":5,"a":0},"o":{"k":100.0,"ix":7,"a":0}}]}]},{"nm":"coin_front","ddd":0,"ty":4,"ind":3,"sr":1.0,"ks":{"a":{"k":[0.445,0.914,0.0],"ix":1,"a":0},"p":{"k":[200.0,200.0,0.0],"ix":2,"a":0},"s":{"k":[100.0,100.0,100.0],"ix":6,"a":0},"r":{"k":0.0,"ix":10,"a":0},"o":{"k":100.0,"ix":11,"a":0}},"ao":0,"ip":0.0,"op":200.0,"st":0.0,"bm":0,"shapes":[{"nm":"null","mn":"ADBE Vector Group","ty":"gr","hd":false,"ix":1,"cix":2,"np":2,"it":[{"nm":"Ellipse Path 1","mn":"ADBE Vector Shape - Ellipse","ty":"el","hd":false,"d":1,"p":{"k":[0.0,0.0],"ix":3,"a":0},"s":{"k":[157.975,157.975],"ix":2,"a":0}},{"nm":"Fill 1","mn":"ADBE Vector Graphic - Fill","ty":"fl","hd":false,"o":{"k":100.0,"ix":5,"a":0},"c":{"k":[1.0,0.5568627715110779,0.9254902005195618,1.0],"ix":4,"a":0},"r":1},{"nm":"Transform","ty":"tr","a":{"k":[0.0,0.0],"ix":1,"a":0},"p":{"k":[0.445,0.914],"ix":2,"a":0},"s":{"k":[100.0,100.0],"ix":3,"a":0},"r":{"k":0.0,"ix":6,"a":0},"sk":{"k":0.0,"ix":4,"a":0},"sa":{"k":0.0,"ix":5,"a":0},"o":{"k":100.0,"ix":7,"a":0}}]}]}]},{"id":"comp_33","layers":[{"nm":"coin_single_quibble","ddd":0,"ty":0,"ind":1,"sr":1.0,"ks":{"a":{"k":[200.0,200.0,0.0],"ix":1,"a":0},"p":{"k":[200.0,200.0,0.0],"ix":2,"a":0},"s":{"k":[100.0,100.0,100.0],"ix":6,"a":0},"r":{"k":0.0,"ix":10,"a":0},"o":{"k":100.0,"ix":11,"a":0}},"ao":0,"ip":0.0,"op":22.0,"st":0.0,"bm":0,"refId":"comp_29","w":400.0,"h":400.0},{"nm":"coin_single_dollar","ddd":0,"ty":0,"ind":2,"sr":1.0,"ks":{"a":{"k":[200.0,200.0,0.0],"ix":1,"a":0},"p":{"k":[200.0,200.0,0.0],"ix":2,"a":0},"s":{"k":[100.0,100.0,100.0],"ix":6,"a":0},"r":{"k":0.0,"ix":10,"a":0},"o":{"k":100.0,"ix":11,"a":0}},"ao":0,"ip":22.0,"op":44.0,"st":22.0,"bm":0,"refId":"comp_34","w":400.0,"h":400.0}]},{"id":"comp_34","layers":[{"nm":"coin_face_dollar","ddd":0,"ty":0,"ind":3,"sr":1.0,"ks":{"a":{"k":[200.0,200.0,0.0],"ix":1,"a":0},"p":{"k":[{"t":0.0,"i":{"x":0.0,"y":1.0},"o":{"x":0.333,"y":0.0},"s":[210.445,200.914,0.0],"e":[200.445,200.914,0.0],"ti":[0.0,0.0,0.0],"to":[0.0,0.0,0.0],"n":"0_1_0p333_0"},{"t":12.0,"i":{"x":0.667,"y":1.0},"o":{"x":1.0,"y":0.0},"s":[200.445,200.914,0.0],"e":[190.0,200.914,0.0],"ti":[0.0,0.0,0.0],"to":[0.0,0.0,0.0],"n":"0p667_1_1_0"},{"t":23.0}],"ix":2,"a":1},"s":{"k":[{"t":0.0,"i":{"x":[0.0,0.667,0.667],"y":[1.0,1.0,1.0]},"o":{"x":[0.333,0.333,0.333],"y":[0.0,0.0,0.0]},"s":[0.0,100.0,100.0],"e":[100.0,100.0,100.0],"n":["0_1_0p333_0","0p667_1_0p333_0","0p667_1_0p333_0"]},{"t":12.0,"i":{"x":[0.667,0.667,0.667],"y":[1.0,1.0,1.0]},"o":{"x":[1.0,0.333,0.333],"y":[0.0,0.0,0.0]},"s":[100.0,100.0,100.0],"e":[0.0,100.0,100.0],"n":["0p667_1_1_0","0p667_1_0p333_0","0p667_1_0p333_0"]},{"t":23.0}],"ix":6,"a":1},"r":{"k":0.0,"ix":10,"a":0},"o":{"k":100.0,"ix":11,"a":0}},"ao":0,"ip":0.0,"op":22.0,"st":0.0,"bm":0,"refId":"comp_35","w":400.0,"h":400.0},{"nm":"coin_back_side_round","ddd":0,"ty":4,"ind":4,"sr":1.0,"ks":{"a":{"k":[0.445,0.914,0.0],"ix":1,"a":0},"p":{"k":[{"t":0.0,"i":{"x":0.0,"y":1.0},"o":{"x":0.333,"y":0.0},"s":[190.445,200.914,0.0],"e":[200.445,200.914,0.0],"ti":[0.0,0.0,0.0],"to":[0.0,0.0,0.0],"n":"0_1_0p333_0"},{"t":12.0,"i":{"x":0.667,"y":1.0},"o":{"x":1.0,"y":0.0},"s":[200.445,200.914,0.0],"e":[210.0,200.914,0.0],"ti":[0.0,0.0,0.0],"to":[0.0,0.0,0.0],"n":"0p667_1_1_0"},{"t":23.0}],"ix":2,"a":1},"s":{"k":[{"t":0.0,"i":{"x":[0.0,0.667,0.667],"y":[1.0,1.0,1.0]},"o":{"x":[0.333,0.333,0.333],"y":[0.0,0.0,0.0]},"s":[0.0,100.0,100.0],"e":[100.0,100.0,100.0],"n":["0_1_0p333_0","0p667_1_0p333_0","0p667_1_0p333_0"]},{"t":12.0,"i":{"x":[0.667,0.667,0.667],"y":[1.0,1.0,1.0]},"o":{"x":[1.0,0.333,0.333],"y":[0.0,0.0,0.0]},"s":[100.0,100.0,100.0],"e":[0.0,100.0,100.0],"n":["0p667_1_1_0","0p667_1_0p333_0","0p667_1_0p333_0"]},{"t":23.0}],"ix":6,"a":1},"r":{"k":0.0,"ix":10,"a":0},"o":{"k":100.0,"ix":11,"a":0}},"ao":0,"ip":0.0,"op":22.0,"st":0.0,"bm":0,"shapes":[{"nm":"null","mn":"ADBE Vector Group","ty":"gr","hd":false,"ix":1,"cix":2,"np":2,"it":[{"nm":"Ellipse Path 1","mn":"ADBE Vector Shape - Ellipse","ty":"el","hd":false,"d":1,"p":{"k":[0.0,0.0],"ix":3,"a":0},"s":{"k":[157.975,157.975],"ix":2,"a":0}},{"nm":"Fill 1","mn":"ADBE Vector Graphic - Fill","ty":"fl","hd":false,"o":{"k":100.0,"ix":5,"a":0},"c":{"k":[0.9960784316062927,0.8967320322990417,0.6980392336845398,1.0],"ix":4,"a":0},"r":1},{"nm":"Transform","ty":"tr","a":{"k":[0.0,0.0],"ix":1,"a":0},"p":{"k":[0.445,0.914],"ix":2,"a":0},"s":{"k":[100.0,100.0],"ix":3,"a":0},"r":{"k":0.0,"ix":6,"a":0},"sk":{"k":0.0,"ix":4,"a":0},"sa":{"k":0.0,"ix":5,"a":0},"o":{"k":100.0,"ix":7,"a":0}}]}]},{"nm":"coin_side","ddd":0,"ty":4,"ind":5,"sr":1.0,"ks":{"a":{"k":[0.5,1.0,0.0],"ix":1,"a":0},"p":{"k":[200.5,201.0,0.0],"ix":2,"a":0},"s":{"k":[100.0,99.7,100.0],"ix":6,"a":0},"r":{"k":0.0,"ix":10,"a":0},"o":{"k":100.0,"ix":11,"a":0}},"ao":0,"ip":0.0,"op":22.0,"st":0.0,"bm":0,"shapes":[{"nm":"null","mn":"ADBE Vector Group","ty":"gr","hd":false,"ix":1,"cix":2,"np":2,"it":[{"nm":"Rectangle Path 1","mn":"ADBE Vector Shape - Rect","ty":"rc","hd":false,"d":1,"p":{"k":[0.0,0.0],"ix":3,"a":0},"s":{"k":[20.5,157.0],"ix":2,"a":0},"r":{"k":0.0,"ix":4,"a":0}},{"nm":"Fill 1","mn":"ADBE Vector Graphic - Fill","ty":"fl","hd":false,"o":{"k":100.0,"ix":5,"a":0},"c":{"k":[0.9960784316062927,0.8967320322990417,0.6980392336845398,1.0],"ix":4,"a":0},"r":1},{"nm":"Transform","ty":"tr","a":{"k":[0.0,0.0],"ix":1,"a":0},"p":{"k":[0.5,1.0],"ix":2,"a":0},"s":{"k":[100.0,100.0],"ix":3,"a":0},"r":{"k":0.0,"ix":6,"a":0},"sk":{"k":0.0,"ix":4,"a":0},"sa":{"k":0.0,"ix":5,"a":0},"o":{"k":100.0,"ix":7,"a":0}}]}]}]},{"id":"comp_35","layers":[{"nm":"dollar","ddd":0,"ty":4,"ind":1,"sr":1.0,"ks":{"a":{"k":[0.0,0.0,0.0],"ix":1,"a":0},"p":{"k":[200.0,200.0,0.0],"ix":2,"a":0},"s":{"k":[100.0,100.0,100.0],"ix":6,"a":0},"r":{"k":0.0,"ix":10,"a":0},"o":{"k":100.0,"ix":11,"a":0}},"ao":0,"ip":0.0,"op":25.0,"st":0.0,"bm":0,"shapes":[{"nm":"null","mn":"ADBE Vector Group","ty":"gr","hd":false,"ix":1,"cix":2,"np":4,"it":[{"nm":"Path 1","mn":"ADBE Vector Shape - Group","ty":"sh","hd":false,"ind":0,"ix":1,"ks":{"k":{"i":[[0.0,3.293],[4.789,1.397],[0.0,0.0]],"o":[[0.0,-3.692],[0.0,0.0],[5.688,-0.799]],"v":[[12.075,14.769],[3.793,7.983],[3.793,21.955]],"c":true},"ix":2,"a":0}},{"nm":"Path 2","mn":"ADBE Vector Shape - Group","ty":"sh","hd":false,"ind":1,"ix":2,"ks":{"k":{"i":[[-4.591,-1.197],[0.0,0.0],[0.0,-3.593]],"o":[[0.0,0.0],[-5.09,0.499],[0.0,3.093]],"v":[[-3.892,-9.181],[-3.892,-21.854],[-11.676,-15.168]],"c":true},"ix":2,"a":0}},{"nm":"Path 3","mn":"ADBE Vector Shape - Group","ty":"sh","hd":false,"ind":2,"ix":3,"ks":{"k":{"i":[[14.67,-1.497],[0.0,0.0],[2.595,0.0],[0.0,2.595],[0.0,0.0],[4.989,3.492],[0.0,2.296],[-3.692,0.0],[-0.998,-0.698],[-4.391,-0.698],[0.0,0.0],[0.0,13.472],[-13.372,1.297],[0.0,0.0],[-2.495,0.0],[0.0,-2.595],[0.0,0.0],[-4.49,-2.794],[0.0,-2.395],[3.593,0.0],[0.998,0.599],[2.895,0.698],[0.0,0.0],[0.0,-13.572]],"o":[[0.0,0.0],[0.0,2.595],[-2.495,0.0],[0.0,0.0],[-7.684,-0.599],[-1.797,-1.198],[0.0,-3.593],[1.396,0.0],[3.293,2.295],[0.0,0.0],[-10.278,-2.495],[0.0,-10.179],[0.0,0.0],[0.0,-2.595],[2.595,0.0],[0.0,0.0],[5.489,0.599],[1.896,1.098],[0.0,3.592],[-1.297,0.0],[-2.595,-1.697],[0.0,0.0],[10.379,2.694],[0.0,10.978]],"v":[[4.69,34.229],[4.69,39.318],[-0.1,44.009],[-4.79,39.318],[-4.79,34.329],[-23.65,27.843],[-26.545,22.254],[-19.958,15.668],[-16.266,16.865],[-4.79,21.655],[-4.79,5.988],[-26.245,-13.971],[-4.79,-34.029],[-4.79,-39.318],[-0.1,-44.009],[4.69,-39.318],[4.69,-33.829],[19.659,-28.84],[22.953,-23.152],[16.366,-16.566],[12.974,-17.563],[4.69,-21.056],[4.69,-7.085],[26.545,13.173]],"c":true},"ix":2,"a":0}},{"nm":"Fill 1","mn":"ADBE Vector Graphic - Fill","ty":"fl","hd":false,"o":{"k":100.0,"ix":5,"a":0},"c":{"k":[1.0,0.5568627715110779,0.9254902005195618,1.0],"ix":4,"a":0},"r":1},{"nm":"Transform","ty":"tr","a":{"k":[0.0,0.0],"ix":1,"a":0},"p":{"k":[0.0,0.0],"ix":2,"a":0},"s":{"k":[100.0,100.0],"ix":3,"a":0},"r":{"k":0.0,"ix":6,"a":0},"sk":{"k":0.0,"ix":4,"a":0},"sa":{"k":0.0,"ix":5,"a":0},"o":{"k":100.0,"ix":7,"a":0}}]}]},{"nm":"coin_middle","ddd":0,"ty":4,"ind":3,"sr":1.0,"ks":{"a":{"k":[0.445,1.417,0.0],"ix":1,"a":0},"p":{"k":[200.0,200.0,0.0],"ix":2,"a":0},"s":{"k":[100.0,100.0,100.0],"ix":6,"a":0},"r":{"k":0.0,"ix":10,"a":0},"o":{"k":100.0,"ix":11,"a":0}},"ao":0,"ip":0.0,"op":25.0,"st":0.0,"bm":0,"shapes":[{"nm":"null","mn":"ADBE Vector Group","ty":"gr","hd":false,"ix":1,"cix":2,"np":2,"it":[{"nm":"Ellipse Path 1","mn":"ADBE Vector Shape - Ellipse","ty":"el","hd":false,"d":1,"p":{"k":[0.0,0.0],"ix":3,"a":0},"s":{"k":[120.746,120.746],"ix":2,"a":0}},{"nm":"Fill 1","mn":"ADBE Vector Graphic - Fill","ty":"fl","hd":false,"o":{"k":100.0,"ix":5,"a":0},"c":{"k":[0.9882352948188782,0.8235294222831726,0.9882352948188782,1.0],"ix":4,"a":0},"r":1},{"nm":"Transform","ty":"tr","a":{"k":[0.0,0.0],"ix":1,"a":0},"p":{"k":[0.445,1.417],"ix":2,"a":0},"s":{"k":[100.0,100.0],"ix":3,"a":0},"r":{"k":0.0,"ix":6,"a":0},"sk":{"k":0.0,"ix":4,"a":0},"sa":{"k":0.0,"ix":5,"a":0},"o":{"k":100.0,"ix":7,"a":0}}]}]},{"nm":"coin_front","ddd":0,"ty":4,"ind":4,"sr":1.0,"ks":{"a":{"k":[0.445,0.914,0.0],"ix":1,"a":0},"p":{"k":[200.0,200.0,0.0],"ix":2,"a":0},"s":{"k":[100.0,100.0,100.0],"ix":6,"a":0},"r":{"k":0.0,"ix":10,"a":0},"o":{"k":100.0,"ix":11,"a":0}},"ao":0,"ip":0.0,"op":25.0,"st":0.0,"bm":0,"shapes":[{"nm":"null","mn":"ADBE Vector Group","ty":"gr","hd":false,"ix":1,"cix":2,"np":2,"it":[{"nm":"Ellipse Path 1","mn":"ADBE Vector Shape - Ellipse","ty":"el","hd":false,"d":1,"p":{"k":[0.0,0.0],"ix":3,"a":0},"s":{"k":[157.975,157.975],"ix":2,"a":0}},{"nm":"Fill 1","mn":"ADBE Vector Graphic - Fill","ty":"fl","hd":false,"o":{"k":100.0,"ix":5,"a":0},"c":{"k":[1.0,0.5568627715110779,0.9254902005195618,1.0],"ix":4,"a":0},"r":1},{"nm":"Transform","ty":"tr","a":{"k":[0.0,0.0],"ix":1,"a":0},"p":{"k":[0.445,0.914],"ix":2,"a":0},"s":{"k":[100.0,100.0],"ix":3,"a":0},"r":{"k":0.0,"ix":6,"a":0},"sk":{"k":0.0,"ix":4,"a":0},"sa":{"k":0.0,"ix":5,"a":0},"o":{"k":100.0,"ix":7,"a":0}}]}]}]},{"id":"comp_36","layers":[{"nm":"coin_single_quibble","ddd":0,"ty":0,"ind":1,"sr":1.0,"ks":{"a":{"k":[200.0,200.0,0.0],"ix":1,"a":0},"p":{"k":[200.0,200.0,0.0],"ix":2,"a":0},"s":{"k":[100.0,100.0,100.0],"ix":6,"a":0},"r":{"k":0.0,"ix":10,"a":0},"o":{"k":100.0,"ix":11,"a":0}},"ao":0,"ip":0.0,"op":22.0,"st":0.0,"bm":0,"refId":"comp_29","w":400.0,"h":400.0},{"nm":"coin_single_yen","ddd":0,"ty":0,"ind":2,"sr":1.0,"ks":{"a":{"k":[200.0,200.0,0.0],"ix":1,"a":0},"p":{"k":[200.0,200.0,0.0],"ix":2,"a":0},"s":{"k":[100.0,100.0,100.0],"ix":6,"a":0},"r":{"k":0.0,"ix":10,"a":0},"o":{"k":100.0,"ix":11,"a":0}},"ao":0,"ip":22.0,"op":44.0,"st":22.0,"bm":0,"refId":"comp_37","w":400.0,"h":400.0}]},{"id":"comp_37","layers":[{"nm":"coin_face_yen","ddd":0,"ty":0,"ind":3,"sr":1.0,"ks":{"a":{"k":[200.0,200.0,0.0],"ix":1,"a":0},"p":{"k":[{"t":0.0,"i":{"x":0.0,"y":1.0},"o":{"x":0.333,"y":0.0},"s":[210.445,200.914,0.0],"e":[200.445,200.914,0.0],"ti":[0.0,0.0,0.0],"to":[0.0,0.0,0.0],"n":"0_1_0p333_0"},{"t":12.0,"i":{"x":0.667,"y":1.0},"o":{"x":1.0,"y":0.0},"s":[200.445,200.914,0.0],"e":[190.0,200.914,0.0],"ti":[0.0,0.0,0.0],"to":[0.0,0.0,0.0],"n":"0p667_1_1_0"},{"t":23.0}],"ix":2,"a":1},"s":{"k":[{"t":0.0,"i":{"x":[0.0,0.667,0.667],"y":[1.0,1.0,1.0]},"o":{"x":[0.333,0.333,0.333],"y":[0.0,0.0,0.0]},"s":[0.0,100.0,100.0],"e":[100.0,100.0,100.0],"n":["0_1_0p333_0","0p667_1_0p333_0","0p667_1_0p333_0"]},{"t":12.0,"i":{"x":[0.667,0.667,0.667],"y":[1.0,1.0,1.0]},"o":{"x":[1.0,0.333,0.333],"y":[0.0,0.0,0.0]},"s":[100.0,100.0,100.0],"e":[0.0,100.0,100.0],"n":["0p667_1_1_0","0p667_1_0p333_0","0p667_1_0p333_0"]},{"t":23.0}],"ix":6,"a":1},"r":{"k":0.0,"ix":10,"a":0},"o":{"k":100.0,"ix":11,"a":0}},"ao":0,"ip":0.0,"op":22.0,"st":0.0,"bm":0,"refId":"comp_38","w":400.0,"h":400.0},{"nm":"coin_back_side_round","ddd":0,"ty":4,"ind":4,"sr":1.0,"ks":{"a":{"k":[0.445,0.914,0.0],"ix":1,"a":0},"p":{"k":[{"t":0.0,"i":{"x":0.0,"y":1.0},"o":{"x":0.333,"y":0.0},"s":[190.445,200.914,0.0],"e":[200.445,200.914,0.0],"ti":[0.0,0.0,0.0],"to":[0.0,0.0,0.0],"n":"0_1_0p333_0"},{"t":12.0,"i":{"x":0.667,"y":1.0},"o":{"x":1.0,"y":0.0},"s":[200.445,200.914,0.0],"e":[210.0,200.914,0.0],"ti":[0.0,0.0,0.0],"to":[0.0,0.0,0.0],"n":"0p667_1_1_0"},{"t":23.0}],"ix":2,"a":1},"s":{"k":[{"t":0.0,"i":{"x":[0.0,0.667,0.667],"y":[1.0,1.0,1.0]},"o":{"x":[0.333,0.333,0.333],"y":[0.0,0.0,0.0]},"s":[0.0,100.0,100.0],"e":[100.0,100.0,100.0],"n":["0_1_0p333_0","0p667_1_0p333_0","0p667_1_0p333_0"]},{"t":12.0,"i":{"x":[0.667,0.667,0.667],"y":[1.0,1.0,1.0]},"o":{"x":[1.0,0.333,0.333],"y":[0.0,0.0,0.0]},"s":[100.0,100.0,100.0],"e":[0.0,100.0,100.0],"n":["0p667_1_1_0","0p667_1_0p333_0","0p667_1_0p333_0"]},{"t":23.0}],"ix":6,"a":1},"r":{"k":0.0,"ix":10,"a":0},"o":{"k":100.0,"ix":11,"a":0}},"ao":0,"ip":0.0,"op":22.0,"st":0.0,"bm":0,"shapes":[{"nm":"null","mn":"ADBE Vector Group","ty":"gr","hd":false,"ix":1,"cix":2,"np":2,"it":[{"nm":"Ellipse Path 1","mn":"ADBE Vector Shape - Ellipse","ty":"el","hd":false,"d":1,"p":{"k":[0.0,0.0],"ix":3,"a":0},"s":{"k":[157.975,157.975],"ix":2,"a":0}},{"nm":"Fill 1","mn":"ADBE Vector Graphic - Fill","ty":"fl","hd":false,"o":{"k":100.0,"ix":5,"a":0},"c":{"k":[0.9960784316062927,0.8967320322990417,0.6980392336845398,1.0],"ix":4,"a":0},"r":1},{"nm":"Transform","ty":"tr","a":{"k":[0.0,0.0],"ix":1,"a":0},"p":{"k":[0.445,0.914],"ix":2,"a":0},"s":{"k":[100.0,100.0],"ix":3,"a":0},"r":{"k":0.0,"ix":6,"a":0},"sk":{"k":0.0,"ix":4,"a":0},"sa":{"k":0.0,"ix":5,"a":0},"o":{"k":100.0,"ix":7,"a":0}}]}]},{"nm":"coin_side","ddd":0,"ty":4,"ind":5,"sr":1.0,"ks":{"a":{"k":[0.5,1.0,0.0],"ix":1,"a":0},"p":{"k":[200.5,201.0,0.0],"ix":2,"a":0},"s":{"k":[100.0,99.7,100.0],"ix":6,"a":0},"r":{"k":0.0,"ix":10,"a":0},"o":{"k":100.0,"ix":11,"a":0}},"ao":0,"ip":0.0,"op":22.0,"st":0.0,"bm":0,"shapes":[{"nm":"null","mn":"ADBE Vector Group","ty":"gr","hd":false,"ix":1,"cix":2,"np":2,"it":[{"nm":"Rectangle Path 1","mn":"ADBE Vector Shape - Rect","ty":"rc","hd":false,"d":1,"p":{"k":[0.0,0.0],"ix":3,"a":0},"s":{"k":[20.5,157.0],"ix":2,"a":0},"r":{"k":0.0,"ix":4,"a":0}},{"nm":"Fill 1","mn":"ADBE Vector Graphic - Fill","ty":"fl","hd":false,"o":{"k":100.0,"ix":5,"a":0},"c":{"k":[0.9960784316062927,0.8967320322990417,0.6980392336845398,1.0],"ix":4,"a":0},"r":1},{"nm":"Transform","ty":"tr","a":{"k":[0.0,0.0],"ix":1,"a":0},"p":{"k":[0.5,1.0],"ix":2,"a":0},"s":{"k":[100.0,100.0],"ix":3,"a":0},"r":{"k":0.0,"ix":6,"a":0},"sk":{"k":0.0,"ix":4,"a":0},"sa":{"k":0.0,"ix":5,"a":0},"o":{"k":100.0,"ix":7,"a":0}}]}]}]},{"id":"comp_38","layers":[{"nm":"coin_yen","ddd":0,"ty":4,"ind":1,"sr":1.0,"ks":{"a":{"k":[0.0,0.001,0.0],"ix":1,"a":0},"p":{"k":[200.0,200.001,0.0],"ix":2,"a":0},"s":{"k":[100.0,100.0,100.0],"ix":6,"a":0},"r":{"k":0.0,"ix":10,"a":0},"o":{"k":100.0,"ix":11,"a":0}},"ao":0,"ip":0.0,"op":25.0,"st":0.0,"bm":0,"shapes":[{"nm":"null","mn":"ADBE Vector Group","ty":"gr","hd":false,"ix":1,"cix":2,"np":2,"it":[{"nm":"Path 1","mn":"ADBE Vector Shape - Group","ty":"sh","hd":false,"ind":0,"ix":1,"ks":{"k":{"i":[[2.7,1.69],[1.7,-2.71],[0.0,0.0],[0.0,0.0],[2.7,-1.7],[-1.7,-2.7],[0.0,0.0],[0.0,0.0],[0.0,-2.61],[-2.61,0.0],[0.0,0.0],[0.0,0.0],[0.0,0.0],[0.0,-2.61],[-2.61,0.0],[0.0,0.0],[0.0,0.0],[-3.19,0.0],[0.0,3.19],[0.0,0.0],[0.0,0.0],[0.0,2.61],[2.61,0.0],[0.0,0.0],[0.0,0.0],[0.0,0.0],[0.0,2.61],[2.61,0.0],[0.0,0.0],[0.0,0.0]],"o":[[-2.7,-1.7],[0.0,0.0],[0.0,0.0],[-1.7,-2.71],[-2.7,1.69],[0.0,0.0],[0.0,0.0],[-2.61,0.0],[0.0,2.61],[0.0,0.0],[0.0,0.0],[0.0,0.0],[-2.61,0.0],[0.0,2.61],[0.0,0.0],[0.0,0.0],[0.0,3.19],[3.19,0.0],[0.0,0.0],[0.0,0.0],[2.61,0.0],[0.0,-2.61],[0.0,0.0],[0.0,0.0],[0.0,0.0],[2.61,0.0],[0.0,-2.61],[0.0,0.0],[0.0,0.0],[1.7,-2.7]],"v":[[24.27,-40.61],[16.3,-38.79],[0.0,-12.83],[-16.3,-38.79],[-24.27,-40.61],[-26.09,-32.65],[-8.8,-5.12],[-21.2,-5.12],[-25.92,-0.39],[-21.2,4.34],[-5.78,4.34],[-5.78,9.01],[-21.2,9.01],[-25.92,13.74],[-21.2,18.47],[-5.78,18.47],[-5.78,35.72],[0.0,41.5],[5.78,35.72],[5.78,18.47],[21.2,18.47],[25.92,13.74],[21.2,9.01],[5.78,9.01],[5.78,4.34],[21.2,4.34],[25.92,-0.39],[21.2,-5.12],[8.8,-5.12],[26.09,-32.65]],"c":true},"ix":2,"a":0}},{"nm":"Fill 1","mn":"ADBE Vector Graphic - Fill","ty":"fl","hd":false,"o":{"k":100.0,"ix":5,"a":0},"c":{"k":[1.0,0.5568627715110779,0.9254902005195618,1.0],"ix":4,"a":0},"r":1},{"nm":"Transform","ty":"tr","a":{"k":[0.0,0.0],"ix":1,"a":0},"p":{"k":[0.0,0.0],"ix":2,"a":0},"s":{"k":[100.0,100.0],"ix":3,"a":0},"r":{"k":0.0,"ix":6,"a":0},"sk":{"k":0.0,"ix":4,"a":0},"sa":{"k":0.0,"ix":5,"a":0},"o":{"k":100.0,"ix":7,"a":0}}]}]},{"nm":"coin_middle","ddd":0,"ty":4,"ind":2,"sr":1.0,"ks":{"a":{"k":[0.445,1.417,0.0],"ix":1,"a":0},"p":{"k":[200.0,200.0,0.0],"ix":2,"a":0},"s":{"k":[100.0,100.0,100.0],"ix":6,"a":0},"r":{"k":0.0,"ix":10,"a":0},"o":{"k":100.0,"ix":11,"a":0}},"ao":0,"ip":0.0,"op":25.0,"st":0.0,"bm":0,"shapes":[{"nm":"null","mn":"ADBE Vector Group","ty":"gr","hd":false,"ix":1,"cix":2,"np":2,"it":[{"nm":"Ellipse Path 1","mn":"ADBE Vector Shape - Ellipse","ty":"el","hd":false,"d":1,"p":{"k":[0.0,0.0],"ix":3,"a":0},"s":{"k":[120.746,120.746],"ix":2,"a":0}},{"nm":"Fill 1","mn":"ADBE Vector Graphic - Fill","ty":"fl","hd":false,"o":{"k":100.0,"ix":5,"a":0},"c":{"k":[0.9882352948188782,0.8235294222831726,0.9882352948188782,1.0],"ix":4,"a":0},"r":1},{"nm":"Transform","ty":"tr","a":{"k":[0.0,0.0],"ix":1,"a":0},"p":{"k":[0.445,1.417],"ix":2,"a":0},"s":{"k":[100.0,100.0],"ix":3,"a":0},"r":{"k":0.0,"ix":6,"a":0},"sk":{"k":0.0,"ix":4,"a":0},"sa":{"k":0.0,"ix":5,"a":0},"o":{"k":100.0,"ix":7,"a":0}}]}]},{"nm":"coin_front","ddd":0,"ty":4,"ind":3,"sr":1.0,"ks":{"a":{"k":[0.445,0.914,0.0],"ix":1,"a":0},"p":{"k":[200.0,200.0,0.0],"ix":2,"a":0},"s":{"k":[100.0,100.0,100.0],"ix":6,"a":0},"r":{"k":0.0,"ix":10,"a":0},"o":{"k":100.0,"ix":11,"a":0}},"ao":0,"ip":0.0,"op":25.0,"st":0.0,"bm":0,"shapes":[{"nm":"null","mn":"ADBE Vector Group","ty":"gr","hd":false,"ix":1,"cix":2,"np":2,"it":[{"nm":"Ellipse Path 1","mn":"ADBE Vector Shape - Ellipse","ty":"el","hd":false,"d":1,"p":{"k":[0.0,0.0],"ix":3,"a":0},"s":{"k":[157.975,157.975],"ix":2,"a":0}},{"nm":"Fill 1","mn":"ADBE Vector Graphic - Fill","ty":"fl","hd":false,"o":{"k":100.0,"ix":5,"a":0},"c":{"k":[1.0,0.5568627715110779,0.9254902005195618,1.0],"ix":4,"a":0},"r":1},{"nm":"Transform","ty":"tr","a":{"k":[0.0,0.0],"ix":1,"a":0},"p":{"k":[0.445,0.914],"ix":2,"a":0},"s":{"k":[100.0,100.0],"ix":3,"a":0},"r":{"k":0.0,"ix":6,"a":0},"sk":{"k":0.0,"ix":4,"a":0},"sa":{"k":0.0,"ix":5,"a":0},"o":{"k":100.0,"ix":7,"a":0}}]}]}]}],"markers":[]}